hcraontario/Hcraontario.py
hcraontario/__init__.py
hcraontario_api-0.1.1.dist-info/LICENSE
hcraontario_api-0.1.1.dist-info/METADATA
hcraontario_api-0.1.1.dist-info/WHEEL
hcraontario_api-0.1.1.dist-info/top_level.txt
hcraontario_api-0.1.1.dist-info/RECORD
