Metadata-Version: 2.1
Name: hcraontario-api
Version: 0.1.1
Summary: The `hcraontario-api` is designed for seamless interaction with the hcraontario.ca API
Home-page: https://github.com/Diego-Arrechea/hcraontario-api
Author: Diego Arrechea
Author-email: diego.arrechea.job@gmail.com
License: MIT
Requires-Python: >=3.6
License-File: LICENSE
Requires-Dist: requests
